{"type":"type_here","message":"message_here","data":{"vehicleSp":{"name":"car","position":{"x":"4,68","y":"0","z":"0"}},"devicesSp":[{"name":"GameObject","position":{"x":"4,67536","y":"1,0234","z":"0,04524"}},{"name":"GameObject (1)","position":{"x":"4,1","y":"1,42128","z":"0,638"}},{"name":"GameObject (2)","position":{"x":"4,44916","y":"1,37024","z":"0,638"}},{"name":"GameObject (3)","position":{"x":"4,79948","y":"1,36908","z":"0,638"}},{"name":"GameObject (4)","position":{"x":"5,53608","y":"1,31572","z":"0,638"}},{"name":"GameObject (5)","position":{"x":"6,210504","y":"1,333004","z":"0,442888"}},{"name":"GameObject (6)","position":{"x":"6,1358","y":"1,12606","z":"0,4814"}},{"name":"GameObject (7)","position":{"x":"4,19976","y":"1,56048","z":"-0,841"}},{"name":"GameObject (8)","position":{"x":"5,19968","y":"1,56048","z":"-0,841"}},{"name":"GameObject (9)","position":{"x":"4,6916","y":"0,918536","z":"-0,48024"}},{"name":"GameObject (10)","position":{"x":"4,6916","y":"1,09764","z":"-1,57296"}},{"name":"GameObject (11)","position":{"x":"4,678376","y":"1,837604","z":"0,201492"}},{"name":"GameObject (12)","position":{"x":"4,678376","y":"1,889572","z":"0,024592"}},{"name":"GameObject (13)","position":{"x":"4,678376","y":"1,889572","z":"0,31436"}},{"name":"GameObject (14)","position":{"x":"4,66608","y":"1,24496","z":"0,50228"}},{"name":"GameObject (15)","position":{"x":"4,307176","y":"1,26932","z":"0,1972"}},{"name":"GameObject (16)","position":{"x":"4,017988","y":"1,26932","z":"0,1972"}},{"name":"GameObject (17)","position":{"x":"3,94224","y":"1,25076","z":"0,33988"}}]}}
